ha_mqtt/__init__.py
ha_mqtt/ha_device.py
ha_mqtt/mqtt_device_base.py
ha_mqtt/mqtt_sensor.py
ha_mqtt/mqtt_siren.py
ha_mqtt/mqtt_switch.py
ha_mqtt/mqtt_thermometer.py
ha_mqtt/py.typed
ha_mqtt/util.py
homeassistant_mqtt_binding-3.0.0.dist-info/LICENSE
homeassistant_mqtt_binding-3.0.0.dist-info/METADATA
homeassistant_mqtt_binding-3.0.0.dist-info/WHEEL
homeassistant_mqtt_binding-3.0.0.dist-info/RECORD
