Metadata-Version: 2.1
Name: homeassistant-mqtt-binding
Version: 3.0.0
Summary: Bindings to implement arbitrary homeassistant devices in python using mqtt as interface
Home-page: https://gitlab.com/anphi/homeassistant-mqtt-binding
License: MIT
Author: Andreas Philipp
Requires-Python: >=3.8,<4.0
Classifier: Development Status :: 4 - Beta
Classifier: License :: OSI Approved :: MIT License
Classifier: Natural Language :: English
Classifier: Operating System :: OS Independent
Classifier: Programming Language :: Python :: 3
Classifier: Programming Language :: Python :: 3.8
Classifier: Programming Language :: Python :: 3.9
Classifier: Programming Language :: Python :: 3.10
Classifier: Programming Language :: Python :: 3.11
Classifier: Programming Language :: Python :: 3.12
Classifier: Topic :: Home Automation
Requires-Dist: paho-mqtt (>=2,<3)
Project-URL: Repository, https://gitlab.com/anphi/homeassistant-mqtt-binding
